LICENSE.md
MANIFEST.in
README.rst
setup.py
acor/__init__.py
acor/_acor.c
acor/acor.c
acor/acor.h
acor/acor.py
acor.egg-info/PKG-INFO
acor.egg-info/SOURCES.txt
acor.egg-info/dependency_links.txt
acor.egg-info/requires.txt
acor.egg-info/top_level.txt