Metadata-Version: 1.0
Name: acor
Version: 1.0.2
Summary: Estimate the autocorrelation time of a time series quickly.
Home-page: http://github.com/dfm/acor/
Author: Daniel Foreman-Mackey and Jonathan Goodman
Author-email: danfm@nyu.edu
License: MIT
Platform: UNKNOWN
Classifier: Development Status :: 3 - Alpha
Classifier: Intended Audience :: Science/Research
Classifier: License :: OSI Approved :: MIT License
Classifier: Operating System :: OS Independent
Classifier: Programming Language :: Python
